py_cupom/__init__.py
py_cupom/py_cupom.py
py_cupom/test_py_cupom.py
py_cupom-0.1.dist-info/DESCRIPTION.rst
py_cupom-0.1.dist-info/METADATA
py_cupom-0.1.dist-info/RECORD
py_cupom-0.1.dist-info/WHEEL
py_cupom-0.1.dist-info/metadata.json
py_cupom-0.1.dist-info/top_level.txt
