Metadata-Version: 2.0
Name: py-cupom
Version: 0.1
Summary: A python script to generate temporary codes with low collision rate.
Home-page: https://github.com/simplificateit/py-cupom
Author: AlexVanAxe
Author-email: alexvanaxe@gmail.com
License: UNKNOWN
Download-URL: https://github.com/simplificateit/py-cupom/tree/0.1
Keywords: cupom,generator,random
Platform: UNKNOWN
